my_package/__init__.py
my_package/sample_module.py
farans_test_package-0.0.1.dist-info/METADATA
farans_test_package-0.0.1.dist-info/WHEEL
farans_test_package-0.0.1.dist-info/top_level.txt
farans_test_package-0.0.1.dist-info/RECORD
