Metadata-Version: 2.1
Name: farans-test-package
Version: 0.0.1
Summary: A sample Python package for testing PyPI
Home-page: https://github.com/faranpde/PyPI-test
Author: Your Name
Author-email: your.email@example.com
License: UNKNOWN
Platform: UNKNOWN
Classifier: Programming Language :: Python :: 3
Classifier: License :: OSI Approved :: MIT License
